booker/__init__.py
booker/ui.py
booker-1.0.1.dist-info/LICENSE
booker-1.0.1.dist-info/METADATA
booker-1.0.1.dist-info/WHEEL
booker-1.0.1.dist-info/top_level.txt
booker-1.0.1.dist-info/RECORD
