Metadata-Version: 2.1
Name: booker
Version: 1.0.1
Summary: Python task scheduling with a simple, English syntax.
Home-page: https://github.com/nvms/booker
Author: nvms
Author-email: jon@pye.rs
License: MIT
Keywords: schedule,scheduling,scheduler,cron,jobcron job,task,cron task,task scheduler,task scheduling
Platform: UNKNOWN
Classifier: Natural Language :: English
Classifier: License :: OSI Approved :: MIT License
Classifier: Programming Language :: Python
Classifier: Programming Language :: Python :: 2.7
Classifier: Programming Language :: Python :: 3
Classifier: Programming Language :: Python :: 3.5
Classifier: Programming Language :: Python :: 3.6
Classifier: Programming Language :: Python :: 3.7
